coordinates_label_photos/__init__.py
coordinates_label_photos/coordinates/__init__.py
coordinates_label_photos/coordinates/coordinates_collection.py
coordinates_label_photos/coordinates/coordinates_test.py
coordinates_label_photos/coordinates/crs_transformer.py
coordinates_label_photos/coordinates/test_coordinates_collection.py
coordinates_label_photos/coordinates/test_crs_transformer.py
coordinates_label_photos/parsers/__init__.py
coordinates_label_photos/parsers/test_parser.py
coordinates_label_photos/parsers/test_parsers.py
coordinates_label_photos/photos/__init__.py
coordinates_label_photos/photos/test_photos.py
coordinates_label_photos/reports/__init__.py
coordinates_label_photos/reports/coordinates_collection.py
coordinates_label_photos/scripts/__init__.py
coordinates_label_photos/scripts/clear_photo_coords.py
coordinates_label_photos/scripts/images_to_gpx.py
coordinates_label_photos/scripts/label_photos.py
coordinates_label_photos/scripts/plot_coords_tracks.py
coordinates_label_photos/scripts/print_exif.py
coordinates_label_photos/scripts/select_closest_photos.py
coordinates_label_photos/scripts/test_label_photos.py
coordinates_label_photos-1.0.7.dist-info/LICENSE
coordinates_label_photos-1.0.7.dist-info/METADATA
coordinates_label_photos-1.0.7.dist-info/WHEEL
coordinates_label_photos-1.0.7.dist-info/entry_points.txt
coordinates_label_photos-1.0.7.dist-info/top_level.txt
coordinates_label_photos-1.0.7.dist-info/RECORD
