Metadata-Version: 2.1
Name: coordinates-label-photos
Version: 1.0.7
Summary: Insert GPS coordinates into pictures EXIF, based on an external track and interpolating timestamp-Plus a few goodies.
Author-email: Alexandre Masselot <alexandre.masselot@gmail.com>
Project-URL: Homepage, https://github.com/terra-submersa/coordinates-label-photos
Project-URL: Bug Tracker, https://github.com/terra-submersa/coordinates-label-photos/issues
Classifier: Programming Language :: Python :: 3
Classifier: License :: OSI Approved :: MIT License
Classifier: Operating System :: OS Independent
Requires-Python: >=3.11
License-File: LICENSE
Requires-Dist: Pillow >=9.1.0
Requires-Dist: tqdm ==4.64.0
Requires-Dist: geopy ==2.2.0
Requires-Dist: gpxpy ==1.5.0
Requires-Dist: pandas ==1.4.3
Requires-Dist: piexif ==1.1.3
Requires-Dist: pyproj ==3.6.0
